[
  {
    "type": "::map::minify",
    "inputSha": [
      {
        "file": "app.js",
        "sha": "f8b4e82361e6950b27dfc97ce426ce1f34d08b08"
      }
    ],
    "outputSha": "ee2dbf9960c557de3d67e3de4eb1d11aba159495",
    "input": "app.js",
    "output": [
      "app.js.map",
      "app.js"
    ]
  },
  {
    "type": "pug@2.0.0-rc.1::map::minify",
    "inputSha": [
      {
        "file": "index.pug",
        "sha": "a1d2208bf614b9c5863b52303101f2bd9b37e2e8"
      }
    ],
    "outputSha": "3825dac235703f52e73faa47dee767188882adde",
    "input": "index.pug",
    "output": [
      "index.html"
    ]
  },
  {
    "type": "::map::minify",
    "inputSha": [
      {
        "file": "styles/_styles.scss",
        "sha": "c85d58962167c8068375b57905305cab97d94eb9"
      }
    ],
    "outputSha": "c85d58962167c8068375b57905305cab97d94eb9",
    "input": "styles/_styles.scss",
    "output": [
      "styles/_styles.scss"
    ]
  },
  {
    "type": "::map::minify",
    "inputSha": [
      {
        "file": "styles/_variables.scss",
        "sha": "07e1f05581d5532af2ae5bbd0674c9bb2e141995"
      }
    ],
    "outputSha": "07e1f05581d5532af2ae5bbd0674c9bb2e141995",
    "input": "styles/_variables.scss",
    "output": [
      "styles/_variables.scss"
    ]
  },
  {
    "type": "node-sass@4.5.3::map::minify",
    "inputSha": [
      {
        "file": "styles/main.scss",
        "sha": "28a64cf28ca0fda5b4f15cc7f0c3d622aea0c1e2"
      },
      {
        "file": "styles/_styles.scss",
        "sha": "c85d58962167c8068375b57905305cab97d94eb9"
      },
      {
        "file": "styles/_variables.scss",
        "sha": "07e1f05581d5532af2ae5bbd0674c9bb2e141995"
      }
    ],
    "outputSha": "8927ab5318a3fec1eacc65cba72e6a5815fef37a",
    "input": "styles/main.scss",
    "output": [
      "styles/main.css.map",
      "styles/main.css"
    ]
  },
  {
    "type": "babel-core@6.24.1::map::minify",
    "inputSha": [
      {
        "file": "scripts/main.babel.js",
        "sha": "b23c609faeb8e2e4e4c09b3bb23ad52f55b70dc1"
      }
    ],
    "outputSha": "1aedba344b0c764bca157c71b9ca0fd61ba3ef40",
    "input": "scripts/main.babel.js",
    "output": [
      "scripts/main.js.map",
      "scripts/main.js"
    ]
  }
]